README.md
pvol.py
setup.py
pvol.egg-info/PKG-INFO
pvol.egg-info/SOURCES.txt
pvol.egg-info/dependency_links.txt
pvol.egg-info/entry_points.txt
pvol.egg-info/requires.txt
pvol.egg-info/top_level.txt