Metadata-Version: 1.0
Name: pvol
Version: 1.6
Summary: CLI PulseAudio volume control
Home-page: https://github.com/mrcl0/pvol
Author: Marcel Pietroń
Author-email: mpietron@mail.com
License: UNKNOWN
Platform: UNKNOWN
